client/__init__.py
client/client.py
commented_out_code/__init__.py
commented_out_code/client.py
commented_out_code/vocab
commented_out_code-0.0.5.dist-info/LICENSE
commented_out_code-0.0.5.dist-info/METADATA
commented_out_code-0.0.5.dist-info/WHEEL
commented_out_code-0.0.5.dist-info/top_level.txt
commented_out_code-0.0.5.dist-info/RECORD
