Metadata-Version: 2.1
Name: commented-out-code
Version: 0.0.5
Summary: A library for commented out code detection
Home-page: https://github.com/w2qiao
Author: qiaowang
Author-email: adawq0@gmail.com
License: UNKNOWN
Platform: UNKNOWN
Classifier: Programming Language :: Python :: 3
Classifier: License :: OSI Approved :: MIT License
Classifier: Operating System :: OS Independent
Requires-Dist: grpcio
Requires-Dist: numpy
Requires-Dist: tensorflow
Requires-Dist: tensorflow-serving-api
